istockphoto/__init__.py
istockphoto/istock.py
istockphoto-0.1.2.dist-info/LICENSE
istockphoto-0.1.2.dist-info/METADATA
istockphoto-0.1.2.dist-info/WHEEL
istockphoto-0.1.2.dist-info/RECORD
