Metadata-Version: 2.1
Name: istockphoto
Version: 0.1.2
Summary: Gracefully download dataset from istockphoto
Home-page: https://github.com/QIN2DIM/istock_downloader
License: Apache-2.0
Keywords: istockphoto,downloader,spider,istock
Author: QIN2DIM
Author-email: yaoqinse@gmail.com
Requires-Python: >=3.8,<4.0
Classifier: License :: OSI Approved :: Apache Software License
Classifier: Programming Language :: Python :: 3
Classifier: Programming Language :: Python :: 3.8
Classifier: Programming Language :: Python :: 3.9
Classifier: Programming Language :: Python :: 3.10
Classifier: Programming Language :: Python :: 3.11
Classifier: Topic :: Scientific/Engineering
Classifier: Topic :: Scientific/Engineering :: Artificial Intelligence
Classifier: Topic :: Scientific/Engineering :: Image Processing
Classifier: Topic :: Scientific/Engineering :: Image Recognition
Classifier: Topic :: Software Development
Classifier: Topic :: Software Development :: Libraries
Classifier: Topic :: Software Development :: Libraries :: Python Modules
Requires-Dist: bs4
Requires-Dist: httpx
Project-URL: Documentation, https://github.com/QIN2DIM/istock_downloader
Project-URL: Repository, https://github.com/QIN2DIM/istock_downloader
